{
  "main": {
    "id": "3cac1f24e63bf61a",
    "type": "split",
    "children": [
      {
        "id": "ae91e193f8d2d831",
        "type": "tabs",
        "children": [
          {
            "id": "34830fbdec25ee07",
            "type": "leaf",
            "state": {
              "type": "markdown",
              "state": {
                "file": "_posts/2023-04-04-TypeScript-5.0-추가된 내용.md",
                "mode": "source",
                "source": false
              }
            }
          }
        ]
      }
    ],
    "direction": "vertical"
  },
  "left": {
    "id": "4ddff3e14be70eda",
    "type": "split",
    "children": [
      {
        "id": "9ebdcc363b5590e7",
        "type": "tabs",
        "children": [
          {
            "id": "4108c21206bbdfbc",
            "type": "leaf",
            "state": {
              "type": "file-explorer",
              "state": {
                "sortOrder": "alphabetical"
              }
            }
          },
          {
            "id": "2833abc333771d19",
            "type": "leaf",
            "state": {
              "type": "search",
              "state": {
                "query": "",
                "matchingCase": false,
                "explainSearch": false,
                "collapseAll": false,
                "extraContext": false,
                "sortOrder": "alphabetical"
              }
            }
          },
          {
            "id": "6567b0a02ccd75c4",
            "type": "leaf",
            "state": {
              "type": "starred",
              "state": {}
            }
          }
        ]
      }
    ],
    "direction": "horizontal",
    "width": 300
  },
  "right": {
    "id": "41c639e8930c77f8",
    "type": "split",
    "children": [
      {
        "id": "77ef09059255f30f",
        "type": "tabs",
        "children": [
          {
            "id": "9e1b50944c5bff93",
            "type": "leaf",
            "state": {
              "type": "backlink",
              "state": {
                "file": "_posts/2023-04-04-TypeScript-5.0-추가된 내용.md",
                "collapseAll": false,
                "extraContext": false,
                "sortOrder": "alphabetical",
                "showSearch": false,
                "searchQuery": "",
                "backlinkCollapsed": false,
                "unlinkedCollapsed": true
              }
            }
          },
          {
            "id": "ca694e7a05cd846a",
            "type": "leaf",
            "state": {
              "type": "outgoing-link",
              "state": {
                "file": "_posts/2023-04-04-TypeScript-5.0-추가된 내용.md",
                "linksCollapsed": false,
                "unlinkedCollapsed": true
              }
            }
          },
          {
            "id": "46e82d4635141029",
            "type": "leaf",
            "state": {
              "type": "tag",
              "state": {
                "sortOrder": "frequency",
                "useHierarchy": true
              }
            }
          },
          {
            "id": "d97cdbcb644674b4",
            "type": "leaf",
            "state": {
              "type": "outline",
              "state": {
                "file": "_posts/2023-04-04-TypeScript-5.0-추가된 내용.md"
              }
            }
          }
        ]
      }
    ],
    "direction": "horizontal",
    "width": 300,
    "collapsed": true
  },
  "left-ribbon": {
    "hiddenItems": {
      "switcher:퀵 스위처 열기": false,
      "graph:그래프 뷰 열기": false,
      "canvas:새 캔버스 만들기": false,
      "daily-notes:오늘의 데일리 노트 열기": false,
      "templates:템플릿 삽입": false,
      "command-palette:명령어 팔레트 열기": false
    }
  },
  "active": "34830fbdec25ee07",
  "lastOpenFiles": [
    "_posts/2023-04-05-TypeScript 5.0 Decorators.md",
    "_posts/2023-04-04-TypeScript-5.0-추가된 내용.md",
    "_posts/2023-04-18-TypeScript 5.0 중요 변경 사항 및 사용 중단.md",
    "_posts/2023-04-17-TypeScript 5.0 속도, 메모리, 패키지 크기 최적화.md",
    "_posts/2023-04-16-TypeScript 5.0 완전한 switch_case 자동완성 기능 추가.md",
    "_posts/2023-04-15-TypeScript 5.0 대소문자 구분 없는 Import 정렬 기능 추가.md",
    "_posts/2023-04-14-TypeScript 5.0 --build 모드에서 Emit-Specific 플래그 전달.md",
    "_posts/2023-04-13-TypeScript 5.0 JSDoc에서 @overload 지원.md",
    "_posts/2023-04-12-TypeScript 5.0 JSDoc에서 @satisfies 지원.md",
    "_posts/2023-04-11-TypeScript 5.0 Support for export type `*`.md",
    "_posts/2023-04-10-TypeScript 5.0 Resolution Customization Flags.md",
    "_posts/2023-04-09-TypeScript 5.0 --moduleResolution bundler.md",
    "_posts/2023-04-08-TypeScript 5.0 Enums.md",
    "_posts/2023-04-07-TypeScript 5.0 Multiple Configuration Files in extends 지원.md",
    "_posts/2023-04-06-TypeScript 5.0 const Type Parameters.md",
    "_posts/2022-11-22-Python 문법 'map','lambda','filter'.md",
    "_posts/2022-11-21-Python 조건문_반복문.md",
    "_posts/2022-11-21-Python 문법 f-string.md",
    "_posts/2022-12-17-var, let, const.md",
    "_posts/2022-12-17-Arrow-function.md",
    "_posts/2022-12-17-Promise.md",
    "_posts/2022-12-17-javascript.md",
    "_posts/2022-12-16-JavaScript의 자료형과 JavaScript만의 특성은 무엇일까?.md",
    "_posts/2022-11-24-javaScript 함수.md",
    "_posts/2022-12-13-Python 풀스택 미니프로젝트 회고.md",
    "_posts/2022-12-10-Python 풀스택 미니프로젝트 1.md",
    "_site/posts/2023-04-02-Unity 기초 와 LifeCycle.html",
    "_site/posts/2023-04-01-Parameter_Argument.html",
    "_site/posts/2023-04-01-Unity Editor Interface.html",
    "_site/posts/2023-04-01-Unity.html",
    "_site/posts/2022-12-16-Arrow-function.html",
    "_site/posts/2022-12-18-if문.html",
    "_site/posts/2023-02-11-6. State and Lifecycle.html",
    "_site/posts/2023-02-11-5. Components and Props.html",
    "_site/posts/2023-02-11-7. State and Lifecycle.html",
    "_site/posts/2023-02-11-4. Rendering Elements.html",
    "_site/assets/img/posts/TCP UDP-1.jpg",
    "_site/assets/img/posts/Pasted image 20230331193302.png",
    "_site/assets/img/posts/Pasted image 20230331193202.png",
    "_site/assets/img/posts/Pasted image 20230331193122.png",
    "_site/assets/img/posts/Pasted image 20230331193053.png",
    "_site/assets/img/posts/Pasted image 20230331192346.png",
    "_site/assets/img/posts/Pasted image 20230331182443.png",
    "_site/assets/img/posts/Pasted image 20230331182256.png",
    "_site/assets/img/posts/Pasted image 20230331182016.png",
    "_site/assets/img/posts/PT.jpeg"
  ]
}